requests2aiohttp
