Metadata-Version: 1.1
Name: requests2aiohttp
Version: 0.8.0
Summary: A compatibility layer to transform requests.Session classes to aiohttp.ClientSession
Home-page: https://github.com/cecton/requests2aiohttp
Author: Cecile Tonglet
Author-email: cecile.tonglet@gmail.com
License: UNKNOWN
Platform: UNKNOWN
Classifier: Development Status :: 3 - Alpha
Classifier: Environment :: Other Environment
Classifier: Intended Audience :: Developers
Classifier: Operating System :: OS Independent
Classifier: Programming Language :: Python
Classifier: Programming Language :: Python :: 3 :: Only
Classifier: Programming Language :: Python :: 3.6
Classifier: Topic :: Utilities
Classifier: License :: OSI Approved :: Apache Software License
